<annotation>
	<folder>narrow_road</folder>
	<filename>Road Narrows Sign_ What Does it Mean_ (1).jpg</filename>
	<path>D:\chaitanya\projects\test_tensorflow\project_main\Sample-Images-main\narrow_road\Road Narrows Sign_ What Does it Mean_ (1).jpg</path>
	<source>
		<database>Unknown</database>
	</source>
	<size>
		<width>664</width>
		<height>1000</height>
		<depth>3</depth>
	</size>
	<segmented>0</segmented>
	<object>
		<name>narrow-road</name>
		<pose>Unspecified</pose>
		<truncated>0</truncated>
		<difficult>0</difficult>
		<bndbox>
			<xmin>67</xmin>
			<ymin>61</ymin>
			<xmax>581</xmax>
			<ymax>537</ymax>
		</bndbox>
	</object>
	<object>
		<name>left turn</name>
		<pose>Unspecified</pose>
		<truncated>0</truncated>
		<difficult>0</difficult>
		<bndbox>
			<xmin>233</xmin>
			<ymin>701</ymin>
			<xmax>267</xmax>
			<ymax>746</ymax>
		</bndbox>
	</object>
	<object>
		<name>right turn</name>
		<pose>Unspecified</pose>
		<truncated>0</truncated>
		<difficult>0</difficult>
		<bndbox>
			<xmin>301</xmin>
			<ymin>685</ymin>
			<xmax>337</xmax>
			<ymax>730</ymax>
		</bndbox>
	</object>
</annotation>
