<annotation>
	<folder>narrow_road</folder>
	<filename>WhatsApp Image 2021-12-15 at 12.33.08 AM (2).jpeg</filename>
	<path>D:\chaitanya\projects\test_tensorflow\project_main\Sample-Images-main\narrow_road\WhatsApp Image 2021-12-15 at 12.33.08 AM (2).jpeg</path>
	<source>
		<database>Unknown</database>
	</source>
	<size>
		<width>180</width>
		<height>280</height>
		<depth>3</depth>
	</size>
	<segmented>0</segmented>
	<object>
		<name>narrow-road</name>
		<pose>Unspecified</pose>
		<truncated>0</truncated>
		<difficult>0</difficult>
		<bndbox>
			<xmin>83</xmin>
			<ymin>58</ymin>
			<xmax>147</xmax>
			<ymax>115</ymax>
		</bndbox>
	</object>
</annotation>
